TimePinner/__init__.py
TimePinner/time_pinner.py
TimePinner-stubs/__init__.pyi
TimePinner-stubs/time_pinner.pyi
TimePinner_stubs-0.0.1.dist-info/LICENSE
TimePinner_stubs-0.0.1.dist-info/METADATA
TimePinner_stubs-0.0.1.dist-info/WHEEL
TimePinner_stubs-0.0.1.dist-info/top_level.txt
TimePinner_stubs-0.0.1.dist-info/RECORD
