Metadata-Version: 2.1
Name: TimePinner-stubs
Version: 0.0.1
Summary: TimePinner的存根
Home-page: https://gitee.com/g1879/TimePinner
Author: g1879
Author-email: g1879@qq.com
License: MIT
Keywords: stopwatch
Classifier: Programming Language :: Python :: 3.6
Classifier: Development Status :: 4 - Beta
Classifier: Topic :: Utilities
Classifier: License :: OSI Approved :: BSD License
Requires-Python: >=3.6
License-File: LICENSE
